{
    "chennai": "MAA",
    "kolkata": "CCU",
    "ahmedabad": "AMD",
    "goa": "GOI",
    "trivandrum": "TRV",
    "calicut": "CCJ",
    "lucknow": "LKO",
    "guwahati": "GAU",
    "jaipur": "JAI",
    "srinagar": "SXR",
    "bhubaneswar": "BBI",
    "coimbatore": "CJB",
    "mangalore": "IXE",
    "trichy": "TRZ",
    "amritsar": "ATQ",
    "varanasi": "VNS",
    "portblair": "IXZ",
    "imphal": "IMF",
    "delhi dial": "DEL",
    "mumbai mial": "BOM",
    "bangalore bial": "BLR",
    "hyderabad ghial": "HYD",
    "cochincial": "COK",
    "nagpur mipl": "NAG",
    "pune": "PNQ",
    "chandigarh": "IXC",
    "patna": "PAT",
    "visakhapatnam": "VTZ",
    "bagdogra": "IXB",
    "madurai": "IXM",
    "aurangabad": "IXU",
    "gaya": "GAY",
    "indore": "IDR",
    "jammu": "IXJ",
    "raipur": "RPR",
    "agartala": "IXA",
    "vadodara": "BDQ",
    "ranchi": "IXR",
    "udaipur": "UDR",
    "bhopal": "BHO",
    "leh": "IXL",
    "dehradun": "DED",
    "rajkot": "RAJ",
    "dibrugarh": "DIB",
    "jodhpur": "JDH",
    "tirupati": "TIR",
    "vijayawada": "VGA",
    "silchar": "IXS",
    "lengpuiaizwal": "AJL",
    "juhu": "VAJJ",
    "rajahmundry": "RJA",
    "bhuj": "BHJ",
    "surat": "STV",
    "jabalpur": "JLR",
    "belgaum": "IXG",
    "tuticorin": "TCR",
    "jamnagar": "JGA",
    "bhavnagar": "BHU",
    "khajuraho": "HJR",
    "guggalkangra": "DHM",
    "allahabad": "IXD",
    "dimapur": "DMU",
    "jorhat": "JRH",
    "hubli": "HBX",
    "agatti": "AGX",
    "diu": "DIU",
    "gorkhpur": "GOP",
    "porbandar": "PBD",
    "agra": "AGR",
    "bhuntar": "KUU",
    "barapani shillong": "SHL",
    "gwalior": "GWL",
    "mysore": "MYQ",
    "lakhimpur lilabari": "IXI",
    "pantnagar": "PGH",
    "sholapur": "SSE",
    "kanpurchakeri": "KNU",
    "darbhanga": "DBR",
    "gorakhpur": "GOP",
    "prayagraj": "IXD",
    "jharsuguda": "JRG",
    "kishangarh": "KQH",
    "gaggalkangra": "DHM",
    "bareilly": "BEK",
    "kolhapur": "KLH",
    "kandla": "IXY",
    "jaisalmer": "JSA",
    "kalaburgi": "GBI",
    "pakyong": "PYG",
    "hindon": "QAH",
    "rupasi": "RUP",
    "bikaner": "BKB",
    "cuddapah": "CDP",
    "pathankot": "IXP",
    "jalgaon": "JLG",
    "tezu": "TEI",
    "tezpur": "TEZ",
    "hyderabadbegumpet": "BPM",
    "salem": "SXV",
    "adampur jalandhar": "AIP",
    "shimla": "SLV",
    "pondicherry": "PNY",
    "ludhiana": "LUH",
    "bhatinda": "BUP",
    "kota": "KTU",
    "coochbehar": "COH",
    "keshod junagarh": "IXK",
    "gondia": "GDB",
    "hollongi donyi polo": "HGI",
    "durgapur": "RDP",
    "nasik hal ozar": "ISK",
    "jagdalpur": "JGB",
    "kurnool": "KJB",
    "bilaspur": "PAB",
    "nanded": "NDC",
    "sindhudurg": "SDW",
    "vijayanagar": "VDY",
    "pasighat": "IXT",
    "bidar": "IXX",
    "bangalore hal": "VOBG",
    "pithoragarh": "NNS",
    "mundra": "VAMA",
    "hisar": "HSS",
    "jamshedpur": "IXW",
    "rourkela": "RRK",
    "jeypore": "PYB",
    "ziro": "ZER",
    "chandigarh jv airpor": "IXC",
    "kannurkial": "CNN",
    "shirdi": "SAG",
    "kushinagar": "KBK",
    "guwahati*": "GAU",
    "chandigarh jv airport": "IXC",
    "tirupathi": "TIR",
    "srinagar*": "SXR",
    "bareillyce": "BEK",
    "adampur jaland": "AIP",
    "barapani shillon": "SHL",
    "lengpuiaizwa": "AJL",
    "trivandrum*": "TRV",
    "goa mopa": "GOX",
    "kolkata*": "CCU",
    "hyderabadbegum": "BPM",
    "international airports\r delhi dial": "DEL",
    "hyderabadbegumpe": "BPM",
    "adampur jal": "AIP",
    "barapani shill": "SHL",
    "lakhimpur l": "IXI",
    "nasik hal o": "ISK",
    "lakhimpur lil": "IXI",
    "s ilchar": "IXS",
    "chandigarh  jv airpo": "IXC",
    "chandigarh*": "IXC",
    "chandigarh  jv airpor": "IXC",
    "chandigarh  jv airport": "IXC",
    "adampur jalan": "AIP",
    "adampur jalandha": "AIP",
    "barapani shillo": "SHL",
    "jammu*": "IXJ",
    "kanpurcivil": "VIKA",
    "lakhimpur lila": "IXI",
    "lakhimpur lilab": "IXI",
    "lakhimpur lilaba": "IXI",
    "nasik hal oza": "ISK",
    "safdarjung": "VIDD"
}